[
    { 
        "id":0,
        "image":"/assets/home/icon1.png",
        "title":"How we help you?",
        "items":["Automations for cluster provisioning.",
        " Production-ready clusters in minutes.",
        "Reactive and proactive support of your clusters and their key components.",
        " 5x8 or 24x7 models."]
    },
    {
        "id":1,
        "image":"/assets/home/icon2.png",
        "title":"What do you achieve?",
        "items":["Self-Service days for teams.",
        "Cloud-native maturity with low investment.",
        "Modernizing IT Operations.",
        "Reduced cost and operational risk."]
    },
    {
        "id":2,
        "image":"/assets/home/icon3.png",
        "title":"Prerequisites",
        "items":["Management committed to operational excellence."]
    }
]